Metadata-Version: 1.1
Name: django-dynamic-formsets
Version: 0.0.7
Summary: A lightweight plugin for managing Django formsets with jQuery.
Home-page: https://github.com/dallasmorningnews/django-dynamic-formsets
Author: Allan James Vestal, The Dallas Morning News
Author-email: ajvestal@dallasnews.com
License: BSD
Download-URL: https://github.com/dallasmorningnews/django-dynamic-formsets/tarball/0.0.7
Keywords: django,formset,javascript
Platform: UNKNOWN
Classifier: Development Status :: 5 - Production/Stable
Classifier: Environment :: Web Environment
Classifier: Framework :: Django
Classifier: Intended Audience :: Developers
Classifier: License :: OSI Approved :: BSD License
Classifier: Operating System :: OS Independent
Classifier: Programming Language :: Python
Classifier: Programming Language :: Python :: 2
Classifier: Programming Language :: Python :: 2.6
Classifier: Programming Language :: Python :: 2.7
